Workbook

Sheet 3-statement model
C2: ="Financial Statement Model for "&D5 -> Financial Statement Model for Apple
C3: $ and shares in millions, except per share data
C5: Company name | D5: Apple
C6: Ticker | D6: AAPL
C7: Circ break 1=off, 0=on | D7: 1
C8: Latest closing share price
C9: Latest closing share price date
C10: Latest fiscal year end date | D10: 43372
C11: Shares outstanding (millions) | D11: 4745398
C12: Select an operating scenario: | D12: Base case
B14: - | C14: INCOME STATEMENT | G14: FORECAST
C15: Fiscal year | D15: =E15-1 -> 2016 | E15: =F15-1 -> 2017 | F15: =YEAR($D$10) -> 2018 | G15: =F15+1 -> 2019 | H15: =G15+1 -> 2020 | I15: =H15+1 -> 2021 | J15: =I15+1 -> 2022 | K15: =J15+1 -> 2023 | M15: 5 year
C16: Fiscal year end date | D16: =EOMONTH(E16,-12) -> 43008 | E16: 43372 | F16: =$D$10 -> 43372 | G16: =EOMONTH(F16,12) -> 43738 | H16: =EOMONTH(G16,12) -> 44104 | I16: =EOMONTH(H16,12) -> 44469 | J16: =EOMONTH(I16,12) -> 44834 | K16: =EOMONTH(J16,12) -> 45199 | M16: CAGR | O16: WSP Comments
C18: Revenue | D18: 215639 | E18: 229234 | F18: 265595 | G18: =F18*(1+G37) -> 252990.48 | H18: =G18*(1+H37) -> 265376.78 | I18: =H18*(1+I37) -> 278407.76 | J18: =I18*(1+J37) -> 293588.36 | K18: =J18*(1+K37) -> 311276.69 | M18: =(K18/F18)^(1/COUNT(G18:K18))-1 -> 0.03225107 | O18: Previous year's revenues x (1+revenue growth rate)
C19: Cost of sales (enter as -) | D19: -131376 | E19: -141048 | F19: -163756 | G19: =G20-G18 -> -157360.08 | H19: =H20-H18 -> -164533.61 | I19: =I20-I18 -> -172056 | J19: =J20-J18 -> -181437.6 | K19: =K20-K18 -> -192369 | O19: Plug = Revenue - Gross Profit
C20: Gross Profit | D20: =SUM(D18:D19) -> 84263 | E20: =SUM(E18:E19) -> 88186 | F20: =SUM(F18:F19) -> 101839 | G20: =G18*G38 -> 95630.402 | H20: =H18*H38 -> 100843.18 | I20: =I18*I38 -> 106351.76 | J20: =J18*J38 -> 112150.75 | K20: =K18*K38 -> 118907.7 | O20: Revenue x Gross Profit Margin forecast
C21: Research & development (enter as -) | D21: -10045 | E21: -11581 | F21: -14236 | G21: =-G18*G39 -> -15685.41 | H21: =-H18*H39 -> -16718.737 | I21: =-I18*I39 -> -17539.689 | J21: =-J18*J39 -> -18496.066 | K21: =-K18*K39 -> -19610.432 | O21: Revenue x R&D % of sales forecast
C22: Selling, general & administrative (enter as -) | D22: -14194 | E22: -15261 | F22: -16705 | G22: =-G18*G40 -> -18721.296 | H22: =-H18*H40 -> -18310.998 | I22: =-I18*I40 -> -19210.135 | J22: =-J18*J40 -> -20257.597 | K22: =-K18*K40 -> -21478.092 | O22: Revenue x SG&A % of sales forecast
C23: Operating profit (EBIT) | D23: =SUM(D20:D22) -> 60024 | E23: =SUM(E20:E22) -> 61344 | F23: =SUM(F20:F22) -> 70898 | G23: =SUM(G20:G22) -> 61223.697 | H23: =SUM(H20:H22) -> 65813.442 | I23: =SUM(I20:I22) -> 69601.94 | J23: =SUM(J20:J22) -> 73397.089 | K23: =SUM(K20:K22) -> 77819.173 | M23: =(K23/F23)^(1/COUNT(G23:K23))-1 -> 0.018803728 | O23: Gross Profit - R&D - SG&A
C24: Interest income | D24: 3999 | E24: 5201 | F24: 5686 | G24: =G221 -> 4701.9145 | H24: =H221 -> 3950.7434 | I24: =I221 -> 3347.1994 | J24: =J221 -> 2820.748 | K24: =K221 -> 2385.0141 | O24: Reference from interest on cash schedule
C25: Interest expense (enter as -) | D25: -1456 | E25: -2323 | F25: -3240 | G25: =-G217-G212 -> -3223.1469 | H25: =-H217-H212 -> -3223.5393 | I25: =-I217-I212 -> -3223.5393 | J25: =-J217-J212 -> -3223.5393 | K25: =-K217-K212 -> -3223.5393 | O25: Reference from interest expense schedule
C26: Other expense, net (enter as -) | D26: -1195 | E26: -133 | F26: -441 | G26: =F26 -> -441 | H26: =G26 -> -441 | I26: =H26 -> -441 | J26: =I26 -> -441 | K26: =J26 -> -441 | O26: Straight-line
C27: Pretax profit | D27: =SUM(D23:D26) -> 61372 | E27: =SUM(E23:E26) -> 64089 | F27: =SUM(F23:F26) -> 72903 | G27: =SUM(G23:G26) -> 62261.464 | H27: =SUM(H23:H26) -> 66099.647 | I27: =SUM(I23:I26) -> 69284.6 | J27: =SUM(J23:J26) -> 72553.298 | K27: =SUM(K23:K26) -> 76539.648 | O27: EBIT + interest income less interest expense less other expense
C28: Taxes (enter expense as -) | D28: -15685 | E28: -15738 | F28: -13372 | G28: =-G27*G41 -> -10397.665 | H28: =-H27*H41 -> -11236.94 | I28: =-I27*I41 -> -11709.097 | J28: =-J27*J41 -> -12261.507 | K28: =-K27*K41 -> -12935.201 | O28: Pre-tax Profit x Tax Rate forecast
C29: Net income | D29: =SUM(D27:D28) -> 45687 | E29: =SUM(E27:E28) -> 48351 | F29: =SUM(F27:F28) -> 59531 | G29: =SUM(G27:G28) -> 51863.8 | H29: =SUM(H27:H28) -> 54862.707 | I29: =SUM(I27:I28) -> 57575.503 | J29: =SUM(J27:J28) -> 60291.791 | K29: =SUM(K27:K28) -> 63604.447 | M29: =(K29/F29)^(1/COUNT(G29:K29))-1 -> 0.013325242 | O29: Pre-tax Profit less taxes
B31: - | C31: Depreciation & amortization | D31: 10505 | E31: 10157 | F31: 10903 | G31: =G171 -> 9459.5504 | H31: =H171 -> 9672.433 | I31: =I171 -> 10302.456 | J31: =J171 -> 11333.642 | K31: =K171 -> 12710.209 | O31: Reference from D&A schedule
C32: EBITDA | D32: =D23+D31 -> 70529 | E32: =E23+E31 -> 71501 | F32: =F23+F31 -> 81801 | G32: =G23+G31 -> 70683.247 | H32: =H23+H31 -> 75485.875 | I32: =I23+I31 -> 79904.396 | J32: =J23+J31 -> 84730.731 | K32: =K23+K31 -> 90529.382 | M32: =(K32/F32)^(1/COUNT(G32:K32))-1 -> 0.020483975 | O32: EBIT + D&A
C33: Stock based compensation | D33: 4210 | E33: 4840 | F33: 5340 | G33: =F33*(1+G37) -> 5086.5761 | H33: =G33*(1+H37) -> 5335.6126 | I33: =H33*(1+I37) -> 5597.6108 | J33: =I33*(1+J37) -> 5902.8288 | K33: =J33*(1+K37) -> 6258.467 | O33: WSP assumption: grow SBC in-line with revenue growth
C34: Adjusted EBITDA | D34: =SUM(D32:D33) -> 74739 | E34: =SUM(E32:E33) -> 76341 | F34: =SUM(F32:F33) -> 87141 | G34: =SUM(G32:G33) -> 75769.823 | H34: =SUM(H32:H33) -> 80821.488 | I34: =SUM(I32:I33) -> 85502.007 | J34: =SUM(J32:J33) -> 90633.56 | K34: =SUM(K32:K33) -> 96787.849 | O34: EBITDA + Stock-based compensation
C36: Growth rates & margins
C37: Revenue growth | E37: =E18/D18-1 -> 0.063045182 | F37: =F18/E18-1 -> 0.15861958 | G37: ='Revenues build-up'!G14 -> -0.047457664 | H37: ='Revenues build-up'!H14 -> 0.048959559 | I37: ='Revenues build-up'!I14 -> 0.049103677 | J37: ='Revenues build-up'!J14 -> 0.054526487 | K37: ='Revenues build-up'!K14 -> 0.060248763 | O37: Scenario analysis schedule below
C38: Gross profit margin | D38: =D20/D18 -> 0.39075956 | E38: =E20/E18 -> 0.3846986 | F38: =F20/F18 -> 0.38343719 | G38: =G241 -> 0.378 | H38: =H241 -> 0.38 | I38: =I241 -> 0.382 | J38: =J241 -> 0.382 | K38: =K241 -> 0.382 | O38: Scenario analysis schedule below
C39: R&D % of sales | D39: =-D21/D18 -> 0.046582483 | E39: =-E21/E18 -> 0.050520429 | F39: =-F21/F18 -> 0.053600407 | G39: =G242 -> 0.062 | H39: =H242 -> 0.063 | I39: =I242 -> 0.063 | J39: =J242 -> 0.063 | K39: =K242 -> 0.063 | O39: Scenario analysis schedule below
C40: SG&A % of sales | D40: =-D22/D18 -> 0.065822973 | E40: =-E22/E18 -> 0.066573894 | F40: =-F22/F18 -> 0.062896515 | G40: =G243 -> 0.074 | H40: =H243 -> 0.069 | I40: =I243 -> 0.069 | J40: =J243 -> 0.069 | K40: =K243 -> 0.069 | O40: Scenario analysis schedule below
C41: Tax rate | D41: =-D28/D27 -> 0.25557257 | E41: =-E28/E27 -> 0.24556476 | F41: =-F28/F27 -> 0.18342181 | G41: 0.167 | H41: 0.17 | I41: 0.169 | J41: =I41 -> 0.169 | K41: =J41 -> 0.169 | O41: Straight line last historical year
B43: - | C43: BALANCE SHEET
C44: =C15 -> Fiscal year | E44: =E15 -> 2017 | F44: =F15 -> 2018 | G44: =G15 -> 2019 | H44: =H15 -> 2020 | I44: =I15 -> 2021 | J44: =J15 -> 2022 | K44: =K15 -> 2023
C45: =C16 -> Fiscal year end date | E45: =E16 -> 43372 | F45: =F16 -> 43372 | G45: =G16 -> 43738 | H45: =H16 -> 44104 | I45: =I16 -> 44469 | J45: =J16 -> 44834 | K45: =K16 -> 45199 | O45: B/S check
C46: Cash & equivalents, ST and LT marketable securities | E46: =20289+53892+194714 -> 268895 | F46: =25913+40388+170799 -> 237100 | G46: =F46+G92 -> 198262.46 | H46: =G46+H92 -> 167547.12 | I46: =H46+I92 -> 142378.75 | J46: =I46+J92 -> 118801.62 | K46: =J46+K92 -> 102033.02 | R46: Reference from 'net change in cash' line on the cash flow statement
C47: Accounts receivable | E47: 17874 | F47: 23186 | G47: =G101 -> 23946.473 | H47: =H101 -> 25493.585 | I47: =I101 -> 26374.162 | J47: =J101 -> 28321.751 | K47: =K101 -> 29669.523 | R47: Grow in-line with revenue growth
C48: Inventories | E48: 4855 | F48: 3956 | G48: =G113 -> 3363.0735 | H48: =H113 -> 4115.7268 | I48: =I113 -> 3531.2063 | J48: =J113 -> 4357.3852 | K48: =K113 -> 3828.5295 | R48: Grow in-line with cost of sales growth
C49: Vendor non-trade receivables | E49: 17799 | F49: 25809 | G49: =F49*(1+G37) -> 24584.165 | H49: =G49*(1+H37) -> 25787.795 | I49: =H49*(1+I37) -> 27054.071 | J49: =I49*(1+J37) -> 28529.234 | K49: =J49*(1+K37) -> 30248.085 | R49: Grow in-line with revenue growth
C50: Other current assets | E50: 13936 | F50: 12087 | G50: =F50*(1+G37) -> 11513.379 | H50: =G50*(1+H37) -> 12077.069 | I50: =H50*(1+I37) -> 12670.098 | J50: =I50*(1+J37) -> 13360.954 | K50: =J50*(1+K37) -> 14165.935 | R50: Grow in-line with revenue growth
C51: Property, plant & equipment | E51: 33783 | F51: 41304 | G51: =G146 -> 46656.375 | H51: =H146 -> 52234.625 | I51: =I146 -> 57431.5 | J51: =J146 -> 62442.314 | K51: =K146 -> 67061.293 | R51: Reference from PP&E schedule
C52: Other non current assets | E52: 18177 | F52: 22283 | G52: =F52*(1+G37) -> 21225.501 | H52: =G52*(1+H37) -> 22264.692 | I52: =H52*(1+I37) -> 23357.97 | J52: =I52*(1+J37) -> 24631.598 | K52: =J52*(1+K37) -> 26115.622 | R52: Grow in-line with revenue growth
C53: Total assets | E53: =SUM(E46:E52) -> 375319 | F53: =SUM(F46:F52) -> 365725 | G53: =SUM(G46:G52) -> 329551.43 | H53: =SUM(H46:H52) -> 309520.61 | I53: =SUM(I46:I52) -> 292797.76 | J53: =SUM(J46:J52) -> 280444.85 | K53: =SUM(K46:K52) -> 273122.01
C55: Accounts payable | E55: 44242 | F55: 55888 | G55: =F55*(G19/F19) -> 53705.147 | H55: =G55*(H19/G19) -> 56153.388 | I55: =H55*(I19/H19) -> 58720.691 | J55: =I55*(J19/I19) -> 61922.524 | K55: =J55*(K19/J19) -> 65653.28 | R55: Grow in-line with cost of sales growth
C56: Other current liabilities | E56: 30551 | F56: 32687 | G56: =F56*(1+G37) -> 31135.751 | H56: =G56*(1+H37) -> 32660.144 | I56: =H56*(1+I37) -> 34263.877 | J56: =I56*(1+J37) -> 36132.166 | K56: =J56*(1+K37) -> 38309.084 | R56: Grow in-line with revenue growth
C57: Deferred revenue (current) | E57: =7548+2836 -> 10384 | F57: =7543+2797 -> 10340 | G57: =F57*(1+G37) -> 9849.2878 | H57: =G57*(1+H37) -> 10331.505 | I57: =H57*(1+I37) -> 10838.819 | J57: =I57*(1+J37) -> 11429.822 | K57: =J57*(1+K37) -> 12118.455 | R57: Grow in-line with revenue growth
C58: Commercial paper / revolver | E58: 11977 | F58: 11964 | G58: =G200 -> 12000 | H58: =H200 -> 12000 | I58: =I200 -> 12000 | J58: =J200 -> 12000 | K58: =K200 -> 12000 | R58: Reference EOP balance from CP/revolver schedule
C59: Long term debt (includes current portion) | E59: =6496+97207 -> 103703 | F59: =8784+93735 -> 102519 | G59: =F59 -> 102519 | H59: =G59 -> 102519 | I59: =H59 -> 102519 | J59: =I59 -> 102519 | K59: =J59 -> 102519 | R59: WSP assumption: straight-line
C60: Other non current liabilities | E60: 40415 | F60: 45180 | G60: =F60*(1+G37) -> 43035.863 | H60: =G60*(1+H37) -> 45142.88 | I60: =H60*(1+I37) -> 47359.561 | J60: =I60*(1+J37) -> 49941.911 | K60: =J60*(1+K37) -> 52950.85 | R60: Grow in-line with revenue growth
C61: Total liabilities | E61: =SUM(E55:E60) -> 241272 | F61: =SUM(F55:F60) -> 258578 | G61: =SUM(G55:G60) -> 252245.05 | H61: =SUM(H55:H60) -> 258806.92 | I61: =SUM(I55:I60) -> 265701.95 | J61: =SUM(J55:J60) -> 273945.42 | K61: =SUM(K55:K60) -> 283550.67
C63: Common stock | E63: 35867 | F63: 40201 | G63: =F63+G33 -> 45287.576 | H63: =G63+H33 -> 50623.189 | I63: =H63+I33 -> 56220.799 | J63: =I63+J33 -> 62123.628 | K63: =J63+K33 -> 68382.095 | R63: Increase by stock-based compensation forecasted in the I/S section
C64: Retained earnings | E64: 98330 | F64: 70400 | G64: =G184 -> 35472.8 | H64: =H184 -> 3544.5064 | I64: =I184 -> -25670.991 | J64: =J184 -> -52170.2 | K64: =K184 -> -75356.753 | R64: Reference from Retained Earnings schedule
C65: Other comprehensive income | E65: -150 | F65: -3454 | G65: =F65 -> -3454 | H65: =G65 -> -3454 | I65: =H65 -> -3454 | J65: =I65 -> -3454 | K65: =J65 -> -3454 | R65: WSP assumption: straight-line
C66: Total equity | E66: =SUM(E63:E65) -> 134047 | F66: =SUM(F63:F65) -> 107147 | G66: =SUM(G63:G65) -> 77306.376 | H66: =SUM(H63:H65) -> 50713.695 | I66: =SUM(I63:I65) -> 27095.809 | J66: =SUM(J63:J65) -> 6499.428 | K66: =SUM(K63:K65) -> -10428.658
C68: Balance check | E68: =ROUND(E53-E61-E66,3) -> 0 | F68: =ROUND(F53-F61-F66,3) -> 0 | G68: =ROUND(G53-G61-G66,3) -> 0 | H68: =ROUND(H53-H61-H66,3) -> 0 | I68: =ROUND(I53-I61-I66,3) -> 0 | J68: =ROUND(J53-J61-J66,3) -> 0 | K68: =ROUND(K53-K61-K66,3) -> 0
B70: - | C70: CASH FLOW STATEMENT
C71: Fiscal year | G71: =G15 -> 2019 | H71: =G71+1 -> 2020 | I71: =H71+1 -> 2021 | J71: =I71+1 -> 2022 | K71: =J71+1 -> 2023
C72: Fiscal year end date | G72: =G16 -> 43738 | H72: =EOMONTH(G72,12) -> 44104 | I72: =EOMONTH(H72,12) -> 44469 | J72: =EOMONTH(I72,12) -> 44834 | K72: =EOMONTH(J72,12) -> 45199
C74: Net income | G74: =G29 -> 51863.8 | H74: =H29 -> 54862.707 | I74: =I29 -> 57575.503 | J74: =J29 -> 60291.791 | K74: =K29 -> 63604.447
C75: Depreciation & amortization | G75: =G31 -> 9459.5504 | H75: =H31 -> 9672.433 | I75: =I31 -> 10302.456 | J75: =J31 -> 11333.642 | K75: =K31 -> 12710.209
C76: Stock based compensation | G76: =G33 -> 5086.5761 | H76: =H33 -> 5335.6126 | I76: =I33 -> 5597.6108 | J76: =J33 -> 5902.8288 | K76: =K33 -> 6258.467
C77: Decreases / (Increases) in working capital assets | G77: =SUM(F47:F50)-SUM(G47:G50) -> 1630.9089 | H77: =SUM(G47:G50)-SUM(H47:H50) -> -4067.085 | I77: =SUM(H47:H50)-SUM(I47:I50) -> -2155.3604 | J77: =SUM(I47:I50)-SUM(J47:J50) -> -4939.7874 | K77: =SUM(J47:J50)-SUM(K47:K50) -> -3342.7483
C78: Increases / (Decreases) in working capital liabilities | G78: =SUM(G55:G57)-SUM(F55:F57) -> -4224.8134 | H78: =SUM(H55:H57)-SUM(G55:G57) -> 4454.8498 | I78: =SUM(I55:I57)-SUM(H55:H57) -> 4678.3512 | J78: =SUM(J55:J57)-SUM(I55:I57) -> 5661.1246 | K78: =SUM(K55:K57)-SUM(J55:J57) -> 6596.3065
C79: =C52 -> Other non current assets | G79: =-G176 -> -469.42624 | H79: =-H176 -> -2640.8741 | I79: =-I176 -> -2773.6097 | J79: =-J176 -> -3045.5821 | K79: =-K176 -> -3362.7354
C80: =C60 -> Other non current liabilities | G80: =G60-F60 -> -2144.1373 | H80: =H60-G60 -> 2107.0169 | I80: =I60-H60 -> 2216.6814 | J80: =J60-I60 -> 2582.3505 | K80: =K60-J60 -> 3008.9384
B81: - | C81: Cash from operating activities | G81: =SUM(G74:G80) -> 61202.458 | H81: =SUM(H74:H80) -> 69724.66 | I81: =SUM(I74:I80) -> 75441.632 | J81: =SUM(J74:J80) -> 77786.367 | K81: =SUM(K74:K80) -> 85472.885
C83: Capital expenditures | G83: =-G144 -> -13285 | H83: =-H144 -> -13649 | I83: =-I144 -> -13819 | J83: =-J144 -> -14572.502 | K83: =-K144 -> -15450.477
C84: Cash from investing activities | G84: =SUM(G83) -> -13285 | H84: =SUM(H83) -> -13649 | I84: =SUM(I83) -> -13819 | J84: =SUM(J83) -> -14572.502 | K84: =SUM(K83) -> -15450.477
C86: =C59 -> Long term debt (includes current portion) | G86: =F59-G59 -> 0 | H86: =G59-H59 -> 0 | I86: =H59-I59 -> 0 | J86: =I59-J59 -> 0 | K86: =J59-K59 -> 0
C87: Commercial paper / revolver | G87: =G58-F58 -> 36 | H87: =H58-G58 -> 0 | I87: =I58-H58 -> 0 | J87: =J58-I58 -> 0 | K87: =K58-J58 -> 0
C88: Share repurchases | G88: =G183 -> -73056 | H88: =H183 -> -73056 | I88: =I183 -> -73056 | J88: =J183 -> -73056 | K88: =K183 -> -73056
C89: Common divedends | G89: =G182 -> -13735 | H89: =H182 -> -13735 | I89: =I182 -> -13735 | J89: =J182 -> -13735 | K89: =K182 -> -13735
C90: Cash from financing activities | G90: =SUM(G86:G89) -> -86755 | H90: =SUM(H86:H89) -> -86791 | I90: =SUM(I86:I89) -> -86791 | J90: =SUM(J86:J89) -> -86791 | K90: =SUM(K86:K89) -> -86791
C92: Net change cash during the period | G92: =G81+G84+G90 -> -38837.542 | H92: =H81+H84+H90 -> -30715.34 | I92: =I81+I84+I90 -> -25168.368 | J92: =J81+J84+J90 -> -23577.135 | K92: =K81+K84+K90 -> -16768.592
B94: - | C94: WORKING CAPITAL
C95: Fiscal year | E95: 2017 | F95: 2018 | G95: 2019 | H95: 2020 | I95: 2021 | J95: 2022 | K95: 2023
C96: Fiscal year end date | E96: 43372 | F96: 43372 | G96: 43738 | H96: 44104 | I96: 44469 | J96: 44834 | K96: 45199
C98: ACCOUNT RECEIVABLES | E98: Historical | G98: Forecast
C99: Beginning of period | G99: =F101 -> 23186 | H99: =G101 -> 23946.473 | I99: =H101 -> 25493.585 | J99: =I101 -> 26374.162 | K99: =J101 -> 28321.751
C100: Increases / (decreases) | G100: =G101-G99 -> 760.4733 | H100: =H101-H99 -> 1547.1118 | I100: =I101-I99 -> 880.57683 | J100: =J101-J99 -> 1947.5892 | K100: =K101-K99 -> 1347.7719
C101: End of period | E101: =E47 -> 17874 | F101: =F47 -> 23186 | G101: =IF($G$105=1,F101*(1+G107),2*G18*G108/365-G99) -> 23946.473 | H101: =IF($G$105=1,G101*(1+H107),2*H18*H108/365-H99) -> 25493.585 | I101: =IF($G$105=1,H101*(1+I107),2*I18*I108/365-I99) -> 26374.162 | J101: =IF($G$105=1,I101*(1+J107),2*J18*J108/365-J99) -> 28321.751 | K101: =IF($G$105=1,J101*(1+K107),2*K18*K108/365-K99) -> 29669.523
C103: Average AR as % of sales | F103: =AVERAGE(E101:F101)/F18 -> 0.077298142 | G103: =AVERAGE(F101:G101)/G18 -> 0.093150685 | H103: =AVERAGE(G101:H101)/H18 -> 0.093150685 | I103: =AVERAGE(H101:I101)/I18 -> 0.093150685 | J103: =AVERAGE(I101:J101)/J18 -> 0.093150685 | K103: =AVERAGE(J101:K101)/K18 -> 0.093150685
C105: Select an AR forecasting approach (1=grow with rev, 2=explicit DSO) | G105: 2
C107: Approach 1: Grow A/R with revenue growth rate | G107: =G37 -> -0.047457664 | H107: =H37 -> 0.048959559 | I107: =I37 -> 0.049103677 | J107: =J37 -> 0.054526487 | K107: =K37 -> 0.060248763
C108: Approach 2: days sales outstanding (DSO) assumption | F108: =F103*365 -> 28.213822 | G108: 34 | H108: 34 | I108: 34 | J108: 34 | K108: 34
C110: Inventories
C111: Beginning of period | G111: =F113 -> 3956 | H111: =G113 -> 3363.0735 | I111: =H113 -> 4115.7268 | J111: =I113 -> 3531.2063 | K111: =J113 -> 4357.3852
C112: Increases / (decreases) | G112: =G113-G111 -> -592.92653 | H112: =H113-H111 -> 752.65334 | I112: =I113-I111 -> -584.52048 | J112: =J113-J111 -> 826.17884 | K112: =K113-K111 -> -528.85563
C113: End of period | E113: =E48 -> 4855 | F113: =F48 -> 3956 | G113: =IF($G$115=1,-2*G117*G19-G111,-G19/G118*2-G111) -> 3363.0735 | H113: =IF($G$115=1,-2*H117*H19-H111,-H19/H118*2-H111) -> 4115.7268 | I113: =IF($G$115=1,-2*I117*I19-I111,-I19/I118*2-I111) -> 3531.2063 | J113: =IF($G$115=1,-2*J117*J19-J111,-J19/J118*2-J111) -> 4357.3852 | K113: =IF($G$115=1,-2*K117*K19-K111,-K19/K118*2-K111) -> 3828.5295
C115: Select an inventory forecasting approach | G115: 2
C117: Approach 1: Keep avg. inventory / COGS ratio constant | F117: =-(AVERAGE(E113:F113)/F19) -> 0.026902831 | G117: =F117 -> 0.026902831 | H117: =G117 -> 0.026902831 | I117: =H117 -> 0.026902831 | J117: =I117 -> 0.026902831 | K117: =J117 -> 0.026902831
C118: Approach 2: Inventory turnover (using 365 day year) | F118: =-F19/AVERAGE(E113:F113) -> 37.170809 | G118: 43 | H118: 44 | I118: 45 | J118: 46 | K118: 47
C120: Working capital ratios / Liquidity
C121: Trade A/R days sales outstanding (average) (DSO) | F121: =365*AVERAGE(E47:F47)/F18 -> 28.213822 | G121: =365*AVERAGE(F47:G47)/G18 -> 34 | H121: =365*AVERAGE(G47:H47)/H18 -> 34 | I121: =365*AVERAGE(H47:I47)/I18 -> 34 | J121: =365*AVERAGE(I47:J47)/J18 -> 34 | K121: =365*AVERAGE(J47:K47)/K18 -> 34
C122: Trade A/R + Non-Trade A/R days sales outstanding (average) | F122: =F121+365*AVERAGE(E49:F49)/F18 -> 58.178467 | G122: =G121+365*AVERAGE(F49:G49)/G18 -> 70.352169 | H122: =H121+365*AVERAGE(G49:H49)/H18 -> 68.64087 | I122: =I121+365*AVERAGE(H49:I49)/I18 -> 68.638548 | J122: =J121+365*AVERAGE(I49:J49)/J18 -> 68.551619 | K122: =K121+365*AVERAGE(J49:K49)/K18 -> 68.460854
C123: Days inventories outstanding (DIO) | F123: =-365*AVERAGE(E48:F48)/F19 -> 9.8195333 | G123: =-365*AVERAGE(F48:G48)/G19 -> 8.4883721 | H123: =-365*AVERAGE(G48:H48)/H19 -> 8.2954545 | I123: =-365*AVERAGE(H48:I48)/I19 -> 8.1111111 | J123: =-365*AVERAGE(I48:J48)/J19 -> 7.9347826 | K123: =-365*AVERAGE(J48:K48)/K19 -> 7.7659574
C124: Operating cycle (inc vendor non-trade A/R) | F124: =SUM(F122:F123) -> 67.998001 | G124: =SUM(G122:G123) -> 78.840541 | H124: =SUM(H122:H123) -> 76.936325 | I124: =SUM(I122:I123) -> 76.749659 | J124: =SUM(J122:J123) -> 76.486402 | K124: =SUM(K122:K123) -> 76.226812
...

Sheet Revenues build-up
C2: Price / volume build | N2: Iphone asp
C3: Fiscal year | D3: 2016 | E3: 2017 | F3: 2018 | G3: 2019 | H3: 2020 | I3: 2021 | J3: 2022 | K3: 2023 | N3: Iphone units number
C4: Fiscal year end date | D4: 43008 | E4: 43372 | F4: 43372 | G4: 43738 | H4: 44104 | I4: 44469 | J4: 44834 | K4: 45199
C5: Revenue by product
C6: Core products:
C7: iPhone | D7: 136700 | E7: 141319 | F7: 166699 | G7: =G17*G22/1000 -> 137570.4 | H7: =H17*H22/1000 -> 138388 | I7: =I17*I22/1000 -> 138388 | J7: =J17*J22/1000 -> 138388 | K7: =K17*K22/1000 -> 138388
C8: iPad | D8: 20628 | E8: 19222 | F8: 18805 | G8: =G18*G23/1000 -> 20222.922 | H8: =H18*H23/1000 -> 20475.904 | I8: =I18*I23/1000 -> 20475.904 | J8: =J18*J23/1000 -> 20475.904 | K8: =K18*K23/1000 -> 20475.904
C9: Mac | D9: 22831 | E9: 25850 | F9: 25484 | G9: =G19*G24/1000 -> 26515.16 | H9: =H19*H24/1000 -> 26642.88 | I9: =I19*I24/1000 -> 26642.88 | J9: =J19*J24/1000 -> 26642.88 | K9: =K19*K24/1000 -> 26642.88
C11: Services | D11: 24348 | E11: 29980 | F11: 37190 | G11: 45603 | H11: 53592 | I11: =H11*(1+I40) -> 62980.56 | J11: =I11*(1+J40) -> 74013.862 | K11: =J11*(1+K40) -> 86980.043 | M11: CG estimates through 2020; WSP thereafter
C12: Other products | D12: 11132 | E12: 12863 | F12: 17417 | G12: 23079 | H12: 26278 | I12: =H12*(1+I41) -> 29920.416 | J12: =I12*(1+J41) -> 34067.711 | K12: =J12*(1+K41) -> 38789.865 | M12: CG estimates through 2020; WSP thereafter
C13: Total revenue | D13: =SUM(D7:D9,D11:D12) -> 215639 | E13: =SUM(E7:E9,E11:E12) -> 229234 | F13: =SUM(F7:F9,F11:F12) -> 265595 | G13: =SUM(G7:G9,G11:G12) -> 252990.48 | H13: =SUM(H7:H9,H11:H12) -> 265376.78 | I13: =SUM(I7:I9,I11:I12) -> 278407.76 | J13: =SUM(J7:J9,J11:J12) -> 293588.36 | K13: =SUM(K7:K9,K11:K12) -> 311276.69
C14: % growth | E14: =E13/D13-1 -> 0.063045182 | F14: =F13/E13-1 -> 0.15861958 | G14: =G13/F13-1 -> -0.047457664 | H14: =H13/G13-1 -> 0.048959559 | I14: =I13/H13-1 -> 0.049103677 | J14: =J13/I13-1 -> 0.054526487 | K14: =K13/J13-1 -> 0.060248763
C16: Units
C17: iPhone | D17: 211884 | E17: 216756 | F17: 217722 | G17: ='3-statement model'!G239 -> 173700 | H17: ='3-statement model'!H239 -> 190880 | I17: ='3-statement model'!I239 -> 190880 | J17: ='3-statement model'!J239 -> 190880 | K17: ='3-statement model'!K239 -> 190880 | M17: CG estimates through 2020; straight line thereafter
C18: iPad | D18: 45590 | E18: 43753 | F18: 43535 | G18: 46170 | H18: 49260 | I18: =H18 -> 49260 | J18: =I18 -> 49260 | K18: =J18 -> 49260 | M18: CG estimates through 2020; straight line thereafter
C19: Mac | D19: 18484 | E19: 19251 | F19: 18209 | G19: 19670 | H19: 19140 | I19: =H19 -> 19140 | J19: =I19 -> 19140 | K19: =J19 -> 19140 | M19: CG estimates through 2020; straight line thereafter
C21: Average selling price
C22: iPhone | D22: =1000*D7/D17 -> 645.16434 | E22: =1000*E7/E17 -> 651.97273 | F22: =1000*F7/F17 -> 765.65069 | G22: ='3-statement model'!G240 -> 792 | H22: ='3-statement model'!H240 -> 725 | I22: ='3-statement model'!I240 -> 725 | J22: ='3-statement model'!J240 -> 725 | K22: ='3-statement model'!K240 -> 725 | M22: CG estimates through 2020; straight line thereafter
C23: iPad | D23: =1000*D8/D18 -> 452.46765 | E23: =1000*E8/E18 -> 439.32987 | F23: =1000*F8/F18 -> 431.9513 | G23: 438.01 | H23: 415.67 | I23: =H23 -> 415.67 | J23: =I23 -> 415.67 | K23: =J23 -> 415.67 | M23: CG estimates through 2020; straight line thereafter
C24: Mac | D24: =1000*D9/D19 -> 1235.1764 | E24: =1000*E9/E19 -> 1342.7874 | F24: =1000*F9/F19 -> 1399.5277 | G24: 1348 | H24: 1392 | I24: =H24 -> 1392 | J24: =I24 -> 1392 | K24: =J24 -> 1392 | M24: CG estimates through 2020; straight line thereafter
C26: Units % growth
C27: iPhone | E27: =E17/D17-1 -> 0.022993714 | F27: =F17/E17-1 -> 0.004456624 | G27: =G17/F17-1 -> -0.20219362 | H27: =H17/G17-1 -> 0.09890616 | I27: =I17/H17-1 -> 0 | J27: =J17/I17-1 -> 0 | K27: =K17/J17-1 -> 0
C28: iPad | E28: =E18/D18-1 -> -0.040293924 | F28: =F18/E18-1 -> -0.0049825155 | G28: =G18/F18-1 -> 0.060526014 | H28: =H18/G18-1 -> 0.066926576 | I28: =I18/H18-1 -> 0 | J28: =J18/I18-1 -> 0 | K28: =K18/J18-1 -> 0
C29: Mac | E29: =E19/D19-1 -> 0.041495347 | F29: =F19/E19-1 -> -0.054127058 | G29: =G19/F19-1 -> 0.080235049 | H29: =H19/G19-1 -> -0.026944586 | I29: =I19/H19-1 -> 0 | J29: =J19/I19-1 -> 0 | K29: =K19/J19-1 -> 0
C31: Average selling price % growth
C32: iPhone | E32: =E22/D22-1 -> 0.010552955 | F32: =F22/E22-1 -> 0.17436 | G32: =G22/F22-1 -> 0.034414268 | H32: =H22/G22-1 -> -0.08459596 | I32: =I22/H22-1 -> 0 | J32: =J22/I22-1 -> 0 | K32: =K22/J22-1 -> 0
C33: iPad | E33: =E23/D23-1 -> -0.029035826 | F33: =F23/E23-1 -> -0.016795059 | G33: =G23/F23-1 -> 0.014026341 | H33: =H23/G23-1 -> -0.051003402 | I33: =I23/H23-1 -> 0 | J33: =J23/I23-1 -> 0 | K33: =K23/J23-1 -> 0
C34: Mac | E34: =E24/D24-1 -> 0.087121986 | F34: =F24/E24-1 -> 0.042255624 | G34: =G24/F24-1 -> -0.036817925 | H34: =H24/G24-1 -> 0.03264095 | I34: =I24/H24-1 -> 0 | J34: =J24/I24-1 -> 0 | K34: =K24/J24-1 -> 0
C36: Revenue growth rate by product
C37: iPhone | E37: =E7/D7-1 -> 0.03378932 | F37: =F7/E7-1 -> 0.17959369 | G37: =G7/F7-1 -> -0.1747377 | H37: =H7/G7-1 -> 0.0059431389 | I37: =I7/H7-1 -> 0 | J37: =J7/I7-1 -> 0 | K37: =K7/J7-1 -> 0
C38: iPad | E38: =E8/D8-1 -> -0.068159783 | F38: =F8/E8-1 -> -0.021693892 | G38: =G8/F8-1 -> 0.075401313 | H38: =H8/G8-1 -> 0.012509691 | I38: =I8/H8-1 -> 0 | J38: =J8/I8-1 -> 0 | K38: =K8/J8-1 -> 0
C39: Mac | E39: =E9/D9-1 -> 0.13223249 | F39: =F9/E9-1 -> -0.014158607 | G39: =G9/F9-1 -> 0.040463036 | H39: =H9/G9-1 -> 0.004816867 | I39: =I9/H9-1 -> 0 | J39: =J9/I9-1 -> 0 | K39: =K9/J9-1 -> 0
C40: Services | E40: =E11/D11-1 -> 0.23131263 | F40: =F11/E11-1 -> 0.24049366 | G40: =G11/F11-1 -> 0.22621672 | H40: =H11/G11-1 -> 0.17518584 | I40: =H40 -> 0.17518584 | J40: =I40 -> 0.17518584 | K40: =J40 -> 0.17518584
C41: Other products | E41: =E12/D12-1 -> 0.15549766 | F41: =F12/E12-1 -> 0.35403872 | G41: =G12/F12-1 -> 0.32508469 | H41: =H12/G12-1 -> 0.13861086 | I41: =H41 -> 0.13861086 | J41: =I41 -> 0.13861086 | K41: =J41 -> 0.13861086

Sheet FSM-2019 update
C2: ="Financial Statement Model for "&D5 -> Financial Statement Model for Apple
C3: $ and shares in millions, except per share data
C5: Company name | D5: Apple
C6: Ticker | D6: AAPL
C7: Circ break 1=off, 0=on | D7: 1
C8: Latest closing share price
C9: Latest closing share price date
C10: Latest fiscal year end date | D10: 43737
C11: Shares outstanding (millions)
C12: Select an operating scenario: | D12: Base case
B14: - | C14: INCOME STATEMENT | H14: FORECAST
C15: Fiscal year | D15: =E15-1 -> 2016 | E15: =F15-1 -> 2017 | F15: =G15-1 -> 2018 | G15: =YEAR($D$10) -> 2019 | H15: =G15+1 -> 2020 | I15: =H15+1 -> 2021 | J15: =I15+1 -> 2022 | K15: =J15+1 -> 2023 | L15: =K15+1 -> 2024 | N15: 5 year
C16: Fiscal year end date | D16: =EOMONTH(E16,-12) -> 42643 | E16: =EOMONTH(F16,-12) -> 43008 | F16: =EOMONTH(G16,-12) -> 43373 | G16: =$D$10 -> 43737 | H16: =EOMONTH(G16,12) -> 44104 | I16: =EOMONTH(H16,12) -> 44469 | J16: =EOMONTH(I16,12) -> 44834 | K16: =EOMONTH(J16,12) -> 45199 | L16: =EOMONTH(K16,12) -> 45565 | N16: CAGR | P16: WSP Comments
C18: Revenue | D18: 215639 | E18: 229234 | F18: 265595 | G18: 260174 | H18: =G18*(1+H37) -> 252990.48 | I18: =H18*(1+I37) -> 265376.78 | J18: =I18*(1+J37) -> 278407.76 | K18: =J18*(1+K37) -> 293588.36 | L18: =K18*(1+L37) -> 311276.69 | N18: =(L18/G18)^(1/COUNT(H18:L18))-1 -> 0.036517268 | P18: Previous year's revenues x (1+revenue growth rate)
C19: Cost of sales (enter as -) | D19: -131376 | E19: -141048 | F19: -163756 | G19: -161782 | H19: =H20-H18 -> -157360.08 | I19: =I20-I18 -> -164533.61 | J19: =J20-J18 -> -172056 | K19: =K20-K18 -> -181437.6 | L19: =L20-L18 -> -192369 | P19: Plug = Revenue - Gross Profit
C20: Gross Profit | D20: =SUM(D18:D19) -> 84263 | E20: =SUM(E18:E19) -> 88186 | F20: =SUM(F18:F19) -> 101839 | G20: =SUM(G18:G19) -> 98392 | H20: =H18*H38 -> 95630.402 | I20: =I18*I38 -> 100843.18 | J20: =J18*J38 -> 106351.76 | K20: =K18*K38 -> 112150.75 | L20: =L18*L38 -> 118907.7 | P20: Revenue x Gross Profit Margin forecast
C21: Research & development (enter as -) | D21: -10045 | E21: -11581 | F21: -14236 | G21: -16217 | H21: =-H18*H39 -> -15685.41 | I21: =-I18*I39 -> -16718.737 | J21: =-J18*J39 -> -17539.689 | K21: =-K18*K39 -> -18496.066 | L21: =-L18*L39 -> -19610.432 | P21: Revenue x R&D % of sales forecast
C22: Selling, general & administrative (enter as -) | D22: -14194 | E22: -15261 | F22: -16705 | G22: -18245 | H22: =-H18*H40 -> -18721.296 | I22: =-I18*I40 -> -18310.998 | J22: =-J18*J40 -> -19210.135 | K22: =-K18*K40 -> -20257.597 | L22: =-L18*L40 -> -21478.092 | P22: Revenue x SG&A % of sales forecast
C23: Operating profit (EBIT) | D23: =SUM(D20:D22) -> 60024 | E23: =SUM(E20:E22) -> 61344 | F23: =SUM(F20:F22) -> 70898 | G23: =SUM(G20:G22) -> 63930 | H23: =SUM(H20:H22) -> 61223.697 | I23: =SUM(I20:I22) -> 65813.442 | J23: =SUM(J20:J22) -> 69601.94 | K23: =SUM(K20:K22) -> 73397.089 | L23: =SUM(L20:L22) -> 77819.173 | N23: =(L23/G23)^(1/COUNT(H23:L23))-1 -> 0.040103078 | P23: Gross Profit - R&D - SG&A
C24: Interest income | D24: 3999 | E24: 5201 | F24: 5686 | G24: 4961 | H24: =H221 -> 4231.5591 | I24: =I221 -> 3685.6987 | J24: =J221 -> 3209.0879 | K24: =K221 -> 2818.3337 | L24: =L221 -> 2527.729 | P24: Reference from interest on cash schedule
C25: Interest expense (enter as -) | D25: -1456 | E25: -2323 | F25: -3240 | G25: -3576 | H25: =-H217-H212 -> -3568.9466 | I25: =-I217-I212 -> -3636.3706 | J25: =-J217-J212 -> -3636.3706 | K25: =-K217-K212 -> -3636.3706 | L25: =-L217-L212 -> -3636.3706 | P25: Reference from interest expense schedule
C26: Other expense, net (enter as -) | D26: -1195 | E26: -133 | F26: -441 | G26: 422 | H26: =G26 -> 422 | I26: =H26 -> 422 | J26: =I26 -> 422 | K26: =J26 -> 422 | L26: =K26 -> 422 | P26: Straight-line
C27: Pretax profit | D27: =SUM(D23:D26) -> 61372 | E27: =SUM(E23:E26) -> 64089 | F27: =SUM(F23:F26) -> 72903 | G27: =SUM(G23:G26) -> 65737 | H27: =SUM(H23:H26) -> 62308.309 | I27: =SUM(I23:I26) -> 66284.771 | J27: =SUM(J23:J26) -> 69596.657 | K27: =SUM(K23:K26) -> 73001.052 | L27: =SUM(L23:L26) -> 77132.531 | P27: EBIT + interest income less interest expense less other expense
C28: Taxes (enter expense as -) | D28: -15685 | E28: -15738 | F28: -13372 | G28: -10481 | H28: =-H27*H41 -> -10405.488 | I28: =-I27*I41 -> -11268.411 | J28: =-J27*J41 -> -11761.835 | K28: =-K27*K41 -> -12337.178 | L28: =-L27*L41 -> -13035.398 | P28: Pre-tax Profit x Tax Rate forecast
C29: Net income | D29: =SUM(D27:D28) -> 45687 | E29: =SUM(E27:E28) -> 48351 | F29: =SUM(F27:F28) -> 59531 | G29: =SUM(G27:G28) -> 55256 | H29: =SUM(H27:H28) -> 51902.821 | I29: =SUM(I27:I28) -> 55016.36 | J29: =SUM(J27:J28) -> 57834.822 | K29: =SUM(K27:K28) -> 60663.874 | L29: =SUM(L27:L28) -> 64097.134 | N29: =(L29/G29)^(1/COUNT(H29:L29))-1 -> 0.030129521 | P29: Pre-tax Profit less taxes
B31: - | C31: Depreciation & amortization | D31: 10505 | E31: 10157 | F31: 10903 | G31: 12547 | H31: =H171 -> 8908.4269 | I31: =I171 -> 9261.0795 | J31: =J171 -> 10114.414 | K31: =K171 -> 11423.77 | L31: =L171 -> 13112.053 | P31: Reference from D&A schedule
C32: EBITDA | D32: =D23+D31 -> 70529 | E32: =E23+E31 -> 71501 | F32: =F23+F31 -> 81801 | G32: =G23+G31 -> 76477 | H32: =H23+H31 -> 70132.123 | I32: =I23+I31 -> 75074.522 | J32: =J23+J31 -> 79716.354 | K32: =K23+K31 -> 84820.859 | L32: =L23+L31 -> 90931.227 | N32: =(L32/G32)^(1/COUNT(H32:L32))-1 -> 0.035229028 | P32: EBIT + D&A
C33: Stock based compensation | D33: 4210 | E33: 4840 | F33: 5340 | G33: 6068 | H33: =G33*(1+H37) -> 5900.4599 | I33: =H33*(1+I37) -> 6189.3438 | J33: =I33*(1+J37) -> 6493.2633 | K33: =J33*(1+K37) -> 6847.3181 | L33: =K33*(1+L37) -> 7259.8606 | P33: WSP assumption: grow SBC in-line with revenue growth
C34: Adjusted EBITDA | D34: =SUM(D32:D33) -> 74739 | E34: =SUM(E32:E33) -> 76341 | F34: =SUM(F32:F33) -> 87141 | G34: =SUM(G32:G33) -> 82545 | H34: =SUM(H32:H33) -> 76032.583 | I34: =SUM(I32:I33) -> 81263.866 | J34: =SUM(J32:J33) -> 86209.617 | K34: =SUM(K32:K33) -> 91668.177 | L34: =SUM(L32:L33) -> 98191.087 | P34: EBITDA + Stock-based compensation
C36: Growth rates & margins
C37: Revenue growth | E37: =E18/D18-1 -> 0.063045182 | F37: =F18/E18-1 -> 0.15861958 | G37: =G18/F18-1 -> -0.020410776 | H37: ='Rev-2019 update'!H14 -> -0.027610439 | I37: ='Rev-2019 update'!I14 -> 0.048959559 | J37: ='Rev-2019 update'!J14 -> 0.049103677 | K37: ='Rev-2019 update'!K14 -> 0.054526487 | L37: ='Rev-2019 update'!L14 -> 0.060248763 | P37: Scenario analysis schedule below
C38: Gross profit margin | D38: =D20/D18 -> 0.39075956 | E38: =E20/E18 -> 0.3846986 | F38: =F20/F18 -> 0.38343719 | G38: =G20/G18 -> 0.37817768 | H38: =H241 -> 0.378 | I38: =I241 -> 0.38 | J38: =J241 -> 0.382 | K38: =K241 -> 0.382 | L38: =L241 -> 0.382 | P38: Scenario analysis schedule below
C39: R&D % of sales | D39: =-D21/D18 -> 0.046582483 | E39: =-E21/E18 -> 0.050520429 | F39: =-F21/F18 -> 0.053600407 | G39: =-G21/G18 -> 0.062331363 | H39: =H242 -> 0.062 | I39: =I242 -> 0.063 | J39: =J242 -> 0.063 | K39: =K242 -> 0.063 | L39: =L242 -> 0.063 | P39: Scenario analysis schedule below
C40: SG&A % of sales | D40: =-D22/D18 -> 0.065822973 | E40: =-E22/E18 -> 0.066573894 | F40: =-F22/F18 -> 0.062896515 | G40: =-G22/G18 -> 0.070126146 | H40: =H243 -> 0.074 | I40: =I243 -> 0.069 | J40: =J243 -> 0.069 | K40: =K243 -> 0.069 | L40: =L243 -> 0.069 | P40: Scenario analysis schedule below
C41: Tax rate | D41: =-D28/D27 -> 0.25557257 | E41: =-E28/E27 -> 0.24556476 | F41: =-F28/F27 -> 0.18342181 | G41: =-G28/G27 -> 0.15943837 | H41: 0.167 | I41: 0.17 | J41: 0.169 | K41: =J41 -> 0.169 | L41: =K41 -> 0.169 | P41: Straight line last historical year
B43: - | C43: BALANCE SHEET
C44: =C15 -> Fiscal year | E44: =E15 -> 2017 | F44: =F15 -> 2018 | G44: =G15 -> 2019 | H44: =H15 -> 2020 | I44: =I15 -> 2021 | J44: =J15 -> 2022 | K44: =K15 -> 2023 | L44: =L15 -> 2024
C45: =C16 -> Fiscal year end date | E45: =E16 -> 43008 | F45: =F16 -> 43373 | G45: =G16 -> 43737 | H45: =H16 -> 44104 | I45: =I16 -> 44469 | J45: =J16 -> 44834 | K45: =K16 -> 45199 | L45: =L16 -> 45565
C46: Cash & equivalents, ST and LT marketable securities | E46: =20289+53892+194714 -> 268895 | F46: =25913+40388+170799 -> 237100 | G46: =48844+51713+105341 -> 205898 | H46: =G46+H92 -> 180545.75 | I46: =H46+I92 -> 156047.73 | J46: =I46+J92 -> 137019.66 | K46: =J46+K92 -> 120362.41 | L46: =K46+L92 -> 110480.41 | P46: Reference from 'net change in cash' line on the cash flow statement
C47: Accounts receivable | E47: 17874 | F47: 23186 | G47: 22926 | H47: =H101 -> 24206.473 | I47: =I101 -> 25233.585 | J47: =J101 -> 26634.162 | K47: =K101 -> 28061.751 | L47: =L101 -> 29929.523 | P47: Grow in-line with revenue growth
C48: Inventories | E48: 4855 | F48: 3956 | G48: 4106 | H48: =H113 -> 3213.0735 | I48: =I113 -> 4265.7268 | J48: =J113 -> 3381.2063 | K48: =K113 -> 4507.3852 | L48: =L113 -> 3678.5295 | P48: Grow in-line with cost of sales growth
C49: Vendor non-trade receivables | E49: 17799 | F49: 25809 | G49: 22878 | H49: =G49*(1+H37) -> 22246.328 | I49: =H49*(1+I37) -> 23335.499 | J49: =I49*(1+J37) -> 24481.358 | K49: =J49*(1+K37) -> 25816.24 | L49: =K49*(1+L37) -> 27371.637 | P49: Grow in-line with revenue growth
C50: Other current assets | E50: 13936 | F50: 12087 | G50: 12352 | H50: =G50*(1+H37) -> 12010.956 | I50: =H50*(1+I37) -> 12599.007 | J50: =I50*(1+J37) -> 13217.665 | K50: =J50*(1+K37) -> 13938.377 | L50: =K50*(1+L37) -> 14778.147 | P50: Grow in-line with revenue growth
C51: Property, plant & equipment | E51: 33783 | F51: 41304 | G51: 37378 | H51: =H146 -> 42967.143 | I51: =I146 -> 48627 | J51: =J146 -> 53665.98 | K51: =K146 -> 58221.864 | L51: =L146 -> 62052.22 | P51: Reference from PP&E schedule
C52: Other non current assets | E52: 18177 | F52: 22283 | G52: 32978 | H52: =G52*(1+H37) -> 32067.463 | I52: =H52*(1+I37) -> 33637.472 | J52: =I52*(1+J37) -> 35289.195 | K52: =J52*(1+K37) -> 37213.391 | L52: =K52*(1+L37) -> 39455.452 | P52: Grow in-line with revenue growth
C53: Total assets | E53: =SUM(E46:E52) -> 375319 | F53: =SUM(F46:F52) -> 365725 | G53: =SUM(G46:G52) -> 338516 | H53: =SUM(H46:H52) -> 317257.19 | I53: =SUM(I46:I52) -> 303746.02 | J53: =SUM(J46:J52) -> 293689.22 | K53: =SUM(K46:K52) -> 288121.42 | L53: =SUM(L46:L52) -> 287745.92
C55: Accounts payable | E55: 44242 | F55: 55888 | G55: 46236 | H55: =G55*(H19/G19) -> 44972.251 | I55: =H55*(I19/H19) -> 47022.387 | J55: =I55*(J19/I19) -> 49172.226 | K55: =J55*(K19/J19) -> 51853.414 | L55: =K55*(L19/K19) -> 54977.518 | P55: Grow in-line with cost of sales growth
C56: Other current liabilities | E56: 30551 | F56: 32687 | G56: 37720 | H56: =G56*(1+H37) -> 36678.534 | I56: =H56*(1+I37) -> 38474.299 | J56: =I56*(1+J37) -> 40363.529 | K56: =J56*(1+K37) -> 42564.41 | L56: =K56*(1+L37) -> 45128.863 | P56: Grow in-line with revenue growth
C57: Deferred revenue (current) | E57: =7548+2836 -> 10384 | F57: =7543+2797 -> 10340 | G57: 5522 | H57: =G57*(1+H37) -> 5369.5352 | I57: =H57*(1+I37) -> 5632.4252 | J57: =I57*(1+J37) -> 5908.998 | K57: =J57*(1+K37) -> 6231.1949 | L57: =K57*(1+L37) -> 6606.6167 | P57: Grow in-line with revenue growth
C58: Commercial paper / revolver | E58: 11977 | F58: 11964 | G58: 5980 | H58: =H200 -> 12000 | I58: =I200 -> 12000 | J58: =J200 -> 12000 | K58: =K200 -> 12000 | L58: =L200 -> 12000 | P58: Reference EOP balance from CP/revolver schedule
C59: Long term debt (includes current portion) | E59: =6496+97207 -> 103703 | F59: =8784+93735 -> 102519 | G59: =91807+10260 -> 102067 | H59: =G59 -> 102067 | I59: =H59 -> 102067 | J59: =I59 -> 102067 | K59: =J59 -> 102067 | L59: =K59 -> 102067 | P59: WSP assumption: straight-line
C60: Other non current liabilities | E60: 40415 | F60: 45180 | G60: 50503 | H60: =G60*(1+H37) -> 49108.59 | I60: =H60*(1+I37) -> 51512.925 | J60: =I60*(1+J37) -> 54042.399 | K60: =J60*(1+K37) -> 56989.141 | L60: =K60*(1+L37) -> 60422.666 | P60: Grow in-line with revenue growth
C61: Total liabilities | E61: =SUM(E55:E60) -> 241272 | F61: =SUM(F55:F60) -> 258578 | G61: =SUM(G55:G60) -> 248028 | H61: =SUM(H55:H60) -> 250195.91 | I61: =SUM(I55:I60) -> 256709.04 | J61: =SUM(J55:J60) -> 263554.15 | K61: =SUM(K55:K60) -> 271705.16 | L61: =SUM(L55:L60) -> 281202.66
C63: Common stock | E63: 35867 | F63: 40201 | G63: 45174 | H63: =G63+H33 -> 51074.46 | I63: =H63+I33 -> 57263.804 | J63: =I63+J33 -> 63757.067 | K63: =J63+K33 -> 70604.385 | L63: =K63+L33 -> 77864.246 | P63: Increase by stock-based compensation forecasted in the I/S section
C64: Retained earnings | E64: 98330 | F64: 70400 | G64: 45898 | H64: =H184 -> 16570.821 | I64: =I184 -> -9642.819 | J64: =J184 -> -33037.997 | K64: =K184 -> -53604.122 | L64: =L184 -> -70736.989 | P64: Reference from Retained Earnings schedule
C65: Other comprehensive income | E65: -150 | F65: -3454 | G65: -584 | H65: =G65 -> -584 | I65: =H65 -> -584 | J65: =I65 -> -584 | K65: =J65 -> -584 | L65: =K65 -> -584 | P65: WSP assumption: straight-line
C66: Total equity | E66: =SUM(E63:E65) -> 134047 | F66: =SUM(F63:F65) -> 107147 | G66: =SUM(G63:G65) -> 90488 | H66: =SUM(H63:H65) -> 67061.281 | I66: =SUM(I63:I65) -> 47036.985 | J66: =SUM(J63:J65) -> 30135.07 | K66: =SUM(K63:K65) -> 16416.263 | L66: =SUM(L63:L65) -> 6543.257
C68: Balance check | E68: =ROUND(E53-E61-E66,3) -> 0 | F68: =ROUND(F53-F61-F66,3) -> 0 | G68: =ROUND(G53-G61-G66,3) -> 0 | H68: =ROUND(H53-H61-H66,3) -> 0 | I68: =ROUND(I53-I61-I66,3) -> 0 | J68: =ROUND(J53-J61-J66,3) -> 0 | K68: =ROUND(K53-K61-K66,3) -> 0 | L68: =ROUND(L53-L61-L66,3) -> 0
B70: - | C70: CASH FLOW STATEMENT
C71: Fiscal year | H71: =H15 -> 2020 | I71: =H71+1 -> 2021 | J71: =I71+1 -> 2022 | K71: =J71+1 -> 2023 | L71: =K71+1 -> 2024
C72: Fiscal year end date | H72: =H16 -> 44104 | I72: =EOMONTH(H72,12) -> 44469 | J72: =EOMONTH(I72,12) -> 44834 | K72: =EOMONTH(J72,12) -> 45199 | L72: =EOMONTH(K72,12) -> 45565
C74: Net income | H74: =H29 -> 51902.821 | I74: =I29 -> 55016.36 | J74: =J29 -> 57834.822 | K74: =K29 -> 60663.874 | L74: =L29 -> 64097.134
C75: Depreciation & amortization | H75: =H31 -> 8908.4269 | I75: =I31 -> 9261.0795 | J75: =J31 -> 10114.414 | K75: =K31 -> 11423.77 | L75: =L31 -> 13112.053
C76: Stock based compensation | H76: =H33 -> 5900.4599 | I76: =I33 -> 6189.3438 | J76: =J33 -> 6493.2633 | K76: =K33 -> 6847.3181 | L76: =L33 -> 7259.8606
C77: Decreases / (Increases) in working capital assets | H77: =SUM(G47:G50)-SUM(H47:H50) -> 585.16898 | I77: =SUM(H47:H50)-SUM(I47:I50) -> -3756.9867 | J77: =SUM(I47:I50)-SUM(J47:J50) -> -2280.5727 | K77: =SUM(J47:J50)-SUM(K47:K50) -> -4609.3633 | L77: =SUM(K47:K50)-SUM(L47:L50) -> -3434.0828
C78: Increases / (Decreases) in working capital liabilities | H78: =SUM(H55:H57)-SUM(G55:G57) -> -2457.68 | I78: =SUM(I55:I57)-SUM(H55:H57) -> 4108.7914 | J78: =SUM(J55:J57)-SUM(I55:I57) -> 4315.641 | K78: =SUM(K55:K57)-SUM(J55:J57) -> 5204.267 | L78: =SUM(L55:L57)-SUM(K55:K57) -> 6063.979
C79: =C52 -> Other non current assets | H79: =-H176 -> -302.03273 | I79: =-I176 -> -2841.9455 | J79: =-J176 -> -2986.117 | K79: =-K176 -> -3331.3491 | L79: =-L176 -> -3733.9933
C80: =C60 -> Other non current liabilities | H80: =H60-G60 -> -1394.41 | I80: =I60-H60 -> 2404.3349 | J80: =J60-I60 -> 2529.474 | K80: =K60-J60 -> 2946.7421 | L80: =L60-K60 -> 3433.5253
B81: - | C81: Cash from operating activities | H81: =SUM(H74:H80) -> 63142.754 | I81: =SUM(I74:I80) -> 70380.977 | J81: =SUM(J74:J80) -> 76020.925 | K81: =SUM(K74:K80) -> 79145.26 | L81: =SUM(L74:L80) -> 86798.476
C83: Capital expenditures | H83: =-H144 -> -13285 | I83: =-I144 -> -13649 | J83: =-J144 -> -13819 | K83: =-K144 -> -14572.502 | L83: =-L144 -> -15450.477
C84: Cash from investing activities | H84: =SUM(H83) -> -13285 | I84: =SUM(I83) -> -13649 | J84: =SUM(J83) -> -13819 | K84: =SUM(K83) -> -14572.502 | L84: =SUM(L83) -> -15450.477
C86: =C59 -> Long term debt (includes current portion) | H86: =G59-H59 -> 0 | I86: =H59-I59 -> 0 | J86: =I59-J59 -> 0 | K86: =J59-K59 -> 0 | L86: =K59-L59 -> 0
C87: Commercial paper / revolver | H87: =H58-G58 -> 6020 | I87: =I58-H58 -> 0 | J87: =J58-I58 -> 0 | K87: =K58-J58 -> 0 | L87: =L58-K58 -> 0
C88: Share repurchases | H88: =H183 -> -67101 | I88: =I183 -> -67101 | J88: =J183 -> -67101 | K88: =K183 -> -67101 | L88: =L183 -> -67101
C89: Common divedends | H89: =H182 -> -14129 | I89: =I182 -> -14129 | J89: =J182 -> -14129 | K89: =K182 -> -14129 | L89: =L182 -> -14129
C90: Cash from financing activities | H90: =SUM(H86:H89) -> -75210 | I90: =SUM(I86:I89) -> -81230 | J90: =SUM(J86:J89) -> -81230 | K90: =SUM(K86:K89) -> -81230 | L90: =SUM(L86:L89) -> -81230
C92: Net change cash during the period | H92: =H81+H84+H90 -> -25352.246 | I92: =I81+I84+I90 -> -24498.023 | J92: =J81+J84+J90 -> -19028.075 | K92: =K81+K84+K90 -> -16657.242 | L92: =L81+L84+L90 -> -9882.0009
B94: - | C94: WORKING CAPITAL
C95: Fiscal year | E95: =F95-1 -> 2017 | F95: =G95-1 -> 2018 | G95: =YEAR($D$10) -> 2019 | H95: =G95+1 -> 2020 | I95: =H95+1 -> 2021 | J95: =I95+1 -> 2022 | K95: =J95+1 -> 2023 | L95: =K95+1 -> 2024
C96: Fiscal year end date | E96: =EOMONTH(F96,-12) -> 43008 | F96: =EOMONTH(G96,-12) -> 43373 | G96: =$D$10 -> 43737 | H96: =EOMONTH(G96,12) -> 44104 | I96: =EOMONTH(H96,12) -> 44469 | J96: =EOMONTH(I96,12) -> 44834 | K96: =EOMONTH(J96,12) -> 45199 | L96: =EOMONTH(K96,12) -> 45565
C98: ACCOUNT RECEIVABLES | F98: Historical | H98: Forecast
C99: Beginning of period | H99: =G101 -> 22926 | I99: =H101 -> 24206.473 | J99: =I101 -> 25233.585 | K99: =J101 -> 26634.162 | L99: =K101 -> 28061.751
C100: Increases / (decreases) | H100: =H101-H99 -> 1280.4733 | I100: =I101-I99 -> 1027.1118 | J100: =J101-J99 -> 1400.5768 | K100: =K101-K99 -> 1427.5892 | L100: =L101-L99 -> 1867.7719
C101: End of period | F101: =F47 -> 23186 | G101: =G47 -> 22926 | H101: =IF($H$105=1,G101*(1+H107),2*H18*H108/365-H99) -> 24206.473 | I101: =IF($H$105=1,H101*(1+I107),2*I18*I108/365-I99) -> 25233.585 | J101: =IF($H$105=1,I101*(1+J107),2*J18*J108/365-J99) -> 26634.162 | K101: =IF($H$105=1,J101*(1+K107),2*K18*K108/365-K99) -> 28061.751 | L101: =IF($H$105=1,K101*(1+L107),2*L18*L108/365-L99) -> 29929.523
C103: Average AR as % of sales | G103: =AVERAGE(F101:G101)/G18 -> 0.088617617 | H103: =AVERAGE(G101:H101)/H18 -> 0.093150685 | I103: =AVERAGE(H101:I101)/I18 -> 0.093150685 | J103: =AVERAGE(I101:J101)/J18 -> 0.093150685 | K103: =AVERAGE(J101:K101)/K18 -> 0.093150685 | L103: =AVERAGE(K101:L101)/L18 -> 0.093150685
C105: Select an AR forecasting approach (1=grow with rev, 2=explicit DSO) | H105: 2
C107: Approach 1: Grow A/R with revenue growth rate | H107: =H37 -> -0.027610439 | I107: =I37 -> 0.048959559 | J107: =J37 -> 0.049103677 | K107: =K37 -> 0.054526487 | L107: =L37 -> 0.060248763
C108: Approach 2: days sales outstanding (DSO) assumption | G108: =G103*365 -> 32.34543 | H108: 34 | I108: 34 | J108: 34 | K108: 34 | L108: 34
C110: Inventories
C111: Beginning of period | H111: =G113 -> 4106 | I111: =H113 -> 3213.0735 | J111: =I113 -> 4265.7268 | K111: =J113 -> 3381.2063 | L111: =K113 -> 4507.3852
C112: Increases / (decreases) | H112: =H113-H111 -> -892.92653 | I112: =I113-I111 -> 1052.6533 | J112: =J113-J111 -> -884.52048 | K112: =K113-K111 -> 1126.1788 | L112: =L113-L111 -> -828.85563
C113: End of period | F113: =F48 -> 3956 | G113: =G48 -> 4106 | H113: =IF($H$115=1,-2*H117*H19-H111,-H19/H118*2-H111) -> 3213.0735 | I113: =IF($H$115=1,-2*I117*I19-I111,-I19/I118*2-I111) -> 4265.7268 | J113: =IF($H$115=1,-2*J117*J19-J111,-J19/J118*2-J111) -> 3381.2063 | K113: =IF($H$115=1,-2*K117*K19-K111,-K19/K118*2-K111) -> 4507.3852 | L113: =IF($H$115=1,-2*L117*L19-L111,-L19/L118*2-L111) -> 3678.5295
C115: Select an inventory forecasting approach | H115: 2
C117: Approach 1: Keep avg. inventory / COGS ratio constant | G117: =-(AVERAGE(F113:G113)/G19) -> 0.024916245 | H117: =G117 -> 0.024916245 | I117: =H117 -> 0.024916245 | J117: =I117 -> 0.024916245 | K117: =J117 -> 0.024916245 | L117: =K117 -> 0.024916245
C118: Approach 2: Inventory turnover (using 365 day year) | G118: =-G19/AVERAGE(F113:G113) -> 40.134458 | H118: 43 | I118: 44 | J118: 45 | K118: 46 | L118: 47
C120: Working capital ratios / Liquidity
C121: Trade A/R days sales outstanding (average) (DSO) | G121: =365*AVERAGE(F47:G47)/G18 -> 32.34543 | H121: =365*AVERAGE(G47:H47)/H18 -> 34 | I121: =365*AVERAGE(H47:I47)/I18 -> 34 | J121: =365*AVERAGE(I47:J47)/J18 -> 34 | K121: =365*AVERAGE(J47:K47)/K18 -> 34 | L121: =365*AVERAGE(K47:L47)/L18 -> 34
C122: Trade A/R + Non-Trade A/R days sales outstanding (average) | G122: =G121+365*AVERAGE(F49:G49)/G18 -> 66.497104 | H122: =H121+365*AVERAGE(G49:H49)/H18 -> 66.551382 | I122: =I121+365*AVERAGE(H49:I49)/I18 -> 65.346689 | J122: =J121+365*AVERAGE(I49:J49)/J18 -> 65.344587 | K122: =K121+365*AVERAGE(J49:K49)/K18 -> 65.265925 | L122: =L121+365*AVERAGE(K49:L49)/L18 -> 65.183791
C123: Days inventories outstanding (DIO) | G123: =-365*AVERAGE(F48:G48)/G19 -> 9.0944295 | H123: =-365*AVERAGE(G48:H48)/H19 -> 8.4883721 | I123: =-365*AVERAGE(H48:I48)/I19 -> 8.2954545 | J123: =-365*AVERAGE(I48:J48)/J19 -> 8.1111111 | K123: =-365*AVERAGE(J48:K48)/K19 -> 7.9347826 | L123: =-365*AVERAGE(K48:L48)/L19 -> 7.7659574
C124: Operating cycle (inc vendor non-trade A/R) | G124: =SUM(G122:G123) -> 75.591533 | H124: =SUM(H122:H123) -> 75.039755 | I124: =SUM(I122:I123) -> 73.642143 | J124: =SUM(J122:J123) -> 73.455698 | K124: =SUM(K122:K123) -> 73.200708 | L124: =SUM(L122:L123) -> 72.949749
...

Sheet Rev-2019 update
C2: Price / volume build | O2: Iphone asp
C3: Fiscal year | D3: =E3-1 -> 2016 | E3: =F3-1 -> 2017 | F3: =G3-1 -> 2018 | G3: =YEAR('FSM-2019 update'!D10) -> 2019 | H3: =G3+1 -> 2020 | I3: =H3+1 -> 2021 | J3: =I3+1 -> 2022 | K3: =J3+1 -> 2023 | L3: =K3+1 -> 2024 | O3: Iphone units number
C4: Fiscal year end date | D4: =EOMONTH(E4,-12) -> 42643 | E4: =EOMONTH(F4,-12) -> 43008 | F4: =EOMONTH(G4,-12) -> 43373 | G4: ='FSM-2019 update'!D10 -> 43737 | H4: =EOMONTH(G4,12) -> 44104 | I4: =EOMONTH(H4,12) -> 44469 | J4: =EOMONTH(I4,12) -> 44834 | K4: =EOMONTH(J4,12) -> 45199 | L4: =EOMONTH(K4,12) -> 45565
C5: Revenue by product
C6: Core products:
C7: iPhone | D7: 136700 | E7: 141319 | F7: 166699 | G7: 142381 | H7: =H17*H22/1000 -> 137570.4 | I7: =I17*I22/1000 -> 138388 | J7: =J17*J22/1000 -> 138388 | K7: =K17*K22/1000 -> 138388 | L7: =L17*L22/1000 -> 138388
C8: iPad | D8: 20628 | E8: 19222 | F8: 18805 | G8: 21280 | H8: =H18*H23/1000 -> 20222.922 | I8: =I18*I23/1000 -> 20475.904 | J8: =J18*J23/1000 -> 20475.904 | K8: =K18*K23/1000 -> 20475.904 | L8: =L18*L23/1000 -> 20475.904
C9: Mac | D9: 22831 | E9: 25850 | F9: 25484 | G9: 25740 | H9: =H19*H24/1000 -> 26515.16 | I9: =I19*I24/1000 -> 26642.88 | J9: =J19*J24/1000 -> 26642.88 | K9: =K19*K24/1000 -> 26642.88 | L9: =L19*L24/1000 -> 26642.88
C11: Services | D11: 24348 | E11: 29980 | F11: 37190 | G11: 46291 | H11: 45603 | I11: 53592 | J11: =I11*(1+J40) -> 62980.56 | K11: =J11*(1+K40) -> 74013.862 | L11: =K11*(1+L40) -> 86980.043 | N11: CG estimates through 2020; WSP thereafter
C12: Other products | D12: 11132 | E12: 12863 | F12: 17417 | G12: 24482 | H12: 23079 | I12: 26278 | J12: =I12*(1+J41) -> 29920.416 | K12: =J12*(1+K41) -> 34067.711 | L12: =K12*(1+L41) -> 38789.865 | N12: CG estimates through 2020; WSP thereafter
C13: Total revenue | D13: =SUM(D7:D9,D11:D12) -> 215639 | E13: =SUM(E7:E9,E11:E12) -> 229234 | F13: =SUM(F7:F9,F11:F12) -> 265595 | G13: =SUM(G7:G9,G11:G12) -> 260174 | H13: =SUM(H7:H9,H11:H12) -> 252990.48 | I13: =SUM(I7:I9,I11:I12) -> 265376.78 | J13: =SUM(J7:J9,J11:J12) -> 278407.76 | K13: =SUM(K7:K9,K11:K12) -> 293588.36 | L13: =SUM(L7:L9,L11:L12) -> 311276.69
C14: % growth | E14: =E13/D13-1 -> 0.063045182 | F14: =F13/E13-1 -> 0.15861958 | G14: =G13/F13-1 -> -0.020410776 | H14: =H13/G13-1 -> -0.027610439 | I14: =I13/H13-1 -> 0.048959559 | J14: =J13/I13-1 -> 0.049103677 | K14: =K13/J13-1 -> 0.054526487 | L14: =L13/K13-1 -> 0.060248763
C16: Units
C17: iPhone | D17: 211884 | E17: 216756 | F17: 217722 | G17: 191000 | H17: ='FSM-2019 update'!H239 -> 173700 | I17: ='FSM-2019 update'!I239 -> 190880 | J17: ='FSM-2019 update'!J239 -> 190880 | K17: ='FSM-2019 update'!K239 -> 190880 | L17: ='FSM-2019 update'!L239 -> 190880 | N17: CG estimates through 2020; straight line thereafter
C18: iPad | D18: 45590 | E18: 43753 | F18: 43535 | G18: 49900 | H18: 46170 | I18: 49260 | J18: =I18 -> 49260 | K18: =J18 -> 49260 | L18: =K18 -> 49260 | N18: CG estimates through 2020; straight line thereafter
C19: Mac | D19: 18484 | E19: 19251 | F19: 18209 | G19: 17500 | H19: 19670 | I19: 19140 | J19: =I19 -> 19140 | K19: =J19 -> 19140 | L19: =K19 -> 19140 | N19: CG estimates through 2020; straight line thereafter
C21: Average selling price
C22: iPhone | D22: =1000*D7/D17 -> 645.16434 | E22: =1000*E7/E17 -> 651.97273 | F22: =1000*F7/F17 -> 765.65069 | G22: =1000*G7/G17 -> 745.45026 | H22: ='FSM-2019 update'!H240 -> 792 | I22: ='FSM-2019 update'!I240 -> 725 | J22: ='FSM-2019 update'!J240 -> 725 | K22: ='FSM-2019 update'!K240 -> 725 | L22: ='FSM-2019 update'!L240 -> 725 | N22: CG estimates through 2020; straight line thereafter
C23: iPad | D23: =1000*D8/D18 -> 452.46765 | E23: =1000*E8/E18 -> 439.32987 | F23: =1000*F8/F18 -> 431.9513 | G23: =1000*G8/G18 -> 426.45291 | H23: 438.01 | I23: 415.67 | J23: =I23 -> 415.67 | K23: =J23 -> 415.67 | L23: =K23 -> 415.67 | N23: CG estimates through 2020; straight line thereafter
C24: Mac | D24: =1000*D9/D19 -> 1235.1764 | E24: =1000*E9/E19 -> 1342.7874 | F24: =1000*F9/F19 -> 1399.5277 | G24: =1000*G9/G19 -> 1470.8571 | H24: 1348 | I24: 1392 | J24: =I24 -> 1392 | K24: =J24 -> 1392 | L24: =K24 -> 1392 | N24: CG estimates through 2020; straight line thereafter
C26: Units % growth
C27: iPhone | E27: =E17/D17-1 -> 0.022993714 | F27: =F17/E17-1 -> 0.004456624 | G27: =G17/F17-1 -> -0.1227345 | H27: =H17/G17-1 -> -0.090575916 | I27: =I17/H17-1 -> 0.09890616 | J27: =J17/I17-1 -> 0 | K27: =K17/J17-1 -> 0 | L27: =L17/K17-1 -> 0
C28: iPad | E28: =E18/D18-1 -> -0.040293924 | F28: =F18/E18-1 -> -0.0049825155 | G28: =G18/F18-1 -> 0.1462042 | H28: =H18/G18-1 -> -0.074749499 | I28: =I18/H18-1 -> 0.066926576 | J28: =J18/I18-1 -> 0 | K28: =K18/J18-1 -> 0 | L28: =L18/K18-1 -> 0
C29: Mac | E29: =E19/D19-1 -> 0.041495347 | F29: =F19/E19-1 -> -0.054127058 | G29: =G19/F19-1 -> -0.038936789 | H29: =H19/G19-1 -> 0.124 | I29: =I19/H19-1 -> -0.026944586 | J29: =J19/I19-1 -> 0 | K29: =K19/J19-1 -> 0 | L29: =L19/K19-1 -> 0
C31: Average selling price % growth
C32: iPhone | E32: =E22/D22-1 -> 0.010552955 | F32: =F22/E22-1 -> 0.17436 | G32: =G22/F22-1 -> -0.02638335 | H32: =H22/G22-1 -> 0.06244513 | I32: =I22/H22-1 -> -0.08459596 | J32: =J22/I22-1 -> 0 | K32: =K22/J22-1 -> 0 | L32: =L22/K22-1 -> 0
C33: iPad | E33: =E23/D23-1 -> -0.029035826 | F33: =F23/E23-1 -> -0.016795059 | G33: =G23/F23-1 -> -0.012729207 | H33: =H23/G23-1 -> 0.027100517 | I33: =I23/H23-1 -> -0.051003402 | J33: =J23/I23-1 -> 0 | K33: =K23/J23-1 -> 0 | L33: =L23/K23-1 -> 0
C34: Mac | E34: =E24/D24-1 -> 0.087121986 | F34: =F24/E24-1 -> 0.042255624 | G34: =G24/F24-1 -> 0.050966791 | H34: =H24/G24-1 -> -0.083527584 | I34: =I24/H24-1 -> 0.03264095 | J34: =J24/I24-1 -> 0 | K34: =K24/J24-1 -> 0 | L34: =L24/K24-1 -> 0
C36: Revenue growth rate by product
C37: iPhone | E37: =E7/D7-1 -> 0.03378932 | F37: =F7/E7-1 -> 0.17959369 | G37: =G7/F7-1 -> -0.1458797 | H37: =H7/G7-1 -> -0.033786811 | I37: =I7/H7-1 -> 0.0059431389 | J37: =J7/I7-1 -> 0 | K37: =K7/J7-1 -> 0 | L37: =L7/K7-1 -> 0
C38: iPad | E38: =E8/D8-1 -> -0.068159783 | F38: =F8/E8-1 -> -0.021693892 | G38: =G8/F8-1 -> 0.13161393 | H38: =H8/G8-1 -> -0.049674732 | I38: =I8/H8-1 -> 0.012509691 | J38: =J8/I8-1 -> 0 | K38: =K8/J8-1 -> 0 | L38: =L8/K8-1 -> 0
C39: Mac | E39: =E9/D9-1 -> 0.13223249 | F39: =F9/E9-1 -> -0.014158607 | G39: =G9/F9-1 -> 0.010045519 | H39: =H9/G9-1 -> 0.030114996 | I39: =I9/H9-1 -> 0.004816867 | J39: =J9/I9-1 -> 0 | K39: =K9/J9-1 -> 0 | L39: =L9/K9-1 -> 0
C40: Services | E40: =E11/D11-1 -> 0.23131263 | F40: =F11/E11-1 -> 0.24049366 | G40: =G11/F11-1 -> 0.24471632 | H40: =H11/G11-1 -> -0.0148625 | I40: =I11/H11-1 -> 0.17518584 | J40: =I40 -> 0.17518584 | K40: =J40 -> 0.17518584 | L40: =K40 -> 0.17518584
C41: Other products | E41: =E12/D12-1 -> 0.15549766 | F41: =F12/E12-1 -> 0.35403872 | G41: =G12/F12-1 -> 0.40563817 | H41: =H12/G12-1 -> -0.05730741 | I41: =I12/H12-1 -> 0.13861086 | J41: =I41 -> 0.13861086 | K41: =J41 -> 0.13861086 | L41: =K41 -> 0.13861086
